yeswehack/__init__.py
yeswehack/api.py
yeswehack/exceptions.py
yeswehack/models.py
yeswehack/version.py
yeswehack-0.8.11.dist-info/METADATA
yeswehack-0.8.11.dist-info/WHEEL
yeswehack-0.8.11.dist-info/RECORD
